libname/__init__.py
LayerViz-0.1.1.dist-info/METADATA
LayerViz-0.1.1.dist-info/WHEEL
LayerViz-0.1.1.dist-info/top_level.txt
LayerViz-0.1.1.dist-info/RECORD
