Metadata-Version: 2.1
Name: LayerViz
Version: 0.1.1
Summary: A Python Library for Visualizing Keras Model that covers a variety of Layers
Home-page: UNKNOWN
Author: Swajay Nandanwade
Author-email: swajaynandanwade@gmail.com
License: UNKNOWN
Keywords: python,keras,visualize,models,layers
Platform: UNKNOWN
Classifier: Programming Language :: Python :: 3
Classifier: License :: OSI Approved :: MIT License
Classifier: Operating System :: OS Independent
Requires-Python: >=3.6
Requires-Dist: graphviz
